anonefiles_uploader/__init__.py
anonefiles_uploader/anonfiles.py
anonfiles_uploader_SockYeh-1.0.1.dist-info/LICENSE
anonfiles_uploader_SockYeh-1.0.1.dist-info/METADATA
anonfiles_uploader_SockYeh-1.0.1.dist-info/WHEEL
anonfiles_uploader_SockYeh-1.0.1.dist-info/top_level.txt
anonfiles_uploader_SockYeh-1.0.1.dist-info/RECORD
