Metadata-Version: 2.1
Name: anonfiles-uploader-SockYeh
Version: 1.0.1
Summary: This is a anonfiles uploader with alot of features.
Home-page: https://github.com/SockYeh/anonfiles-uploader
Author: SockYeh
Author-email: author@example.com
License: UNKNOWN
Project-URL: Bug Tracker, https://github.com/SockYeh/anonfiles-uploader/issues
Platform: UNKNOWN
Classifier: Programming Language :: Python :: 3
Classifier: License :: OSI Approved :: MIT License
Classifier: Operating System :: OS Independent
Requires-Python: >=3.6
License-File: LICENSE
